lcmd_db/__init__.py
lcmd_db/client.py
lcmd_db/exceptions.py
lcmd_db/py.typed
lcmd_db/types.py
lcmd_db-0.1.0.dist-info/METADATA
lcmd_db-0.1.0.dist-info/WHEEL
lcmd_db-0.1.0.dist-info/licenses/LICENSE
lcmd_db-0.1.0.dist-info/RECORD
