Metadata-Version: 2.4
Name: lcmd-db
Version: 0.1.0
Summary: Python client for the LCMD molecular database
Project-URL: Homepage, https://lcmd-app.epfl.ch
Project-URL: Documentation, https://lcmd-app.epfl.ch/docs
Project-URL: Source, https://github.com/lcmd-epfl/db
Project-URL: Changelog, https://github.com/lcmd-epfl/db/blob/master/CHANGELOG.md
Project-URL: Bug Tracker, https://github.com/lcmd-epfl/db/issues
Author-email: Romain Graux <author@romaingrx.com>
License: MIT
License-File: LICENSE
Keywords: chemistry,lcmd,molecular-database,quantum-chemistry
Classifier: Development Status :: 4 - Beta
Classifier: Intended Audience :: Science/Research
Classifier: License :: OSI Approved :: MIT License
Classifier: Programming Language :: Python :: 3
Classifier: Programming Language :: Python :: 3.9
Classifier: Programming Language :: Python :: 3.10
Classifier: Programming Language :: Python :: 3.11
Classifier: Programming Language :: Python :: 3.12
Classifier: Programming Language :: Python :: 3.13
Classifier: Topic :: Scientific/Engineering :: Chemistry
Classifier: Typing :: Typed
Requires-Python: >=3.9
Requires-Dist: platformdirs>=4.0.0
Requires-Dist: polars>=0.20.0
Requires-Dist: pooch>=1.8.0
Requires-Dist: pyarrow>=14.0.0
Requires-Dist: tqdm>=4.67.1
